kilroy_face_reddit/__init__.py
kilroy_face_reddit/__main__.py
kilroy_face_reddit/config.py
kilroy_face_reddit/face.py
kilroy_face_reddit/log.py
kilroy_face_reddit/models.py
kilroy_face_reddit/post.py
kilroy_face_reddit/posters.py
kilroy_face_reddit/processors.py
kilroy_face_reddit/resources/__init__.py
kilroy_face_reddit/resources/config.yaml
kilroy_face_reddit/restrictions.py
kilroy_face_reddit/scoring/__init__.py
kilroy_face_reddit/scoring/modifiers.py
kilroy_face_reddit/scoring/raw.py
kilroy_face_reddit/scraping/__init__.py
kilroy_face_reddit/scraping/base.py
kilroy_face_reddit/scraping/frontpage/__init__.py
kilroy_face_reddit/scraping/frontpage/scraper.py
kilroy_face_reddit/scraping/frontpage/sorting.py
kilroy_face_reddit/utils.py
kilroy_face_reddit-0.1.2.dist-info/entry_points.txt
kilroy_face_reddit-0.1.2.dist-info/LICENSE
kilroy_face_reddit-0.1.2.dist-info/WHEEL
kilroy_face_reddit-0.1.2.dist-info/METADATA
kilroy_face_reddit-0.1.2.dist-info/RECORD
